{"date":"2026-06-20","rooms":{"小米官方手环直播间":{"_hourly_stats":{"0":{"orders":18,"revenue":5437.9,"products":{"REDMI Watch 6":{"orders":1,"revenue":539.0,"avg_price":0},"小米手环10":{"orders":15,"revenue":4165.0,"avg_price":277.67},"小米手环10 Pro":{"orders":2,"revenue":733.9,"avg_price":0}}},"1":{"orders":5,"revenue":1415.66,"products":{"REDMI 手环 3":{"orders":1,"revenue":137.0,"avg_price":0},"小米手环10":{"orders":2,"revenue":480.66,"avg_price":0},"小米手环10 Pro":{"orders":2,"revenue":798.0,"avg_price":0}}},"2":{"orders":6,"revenue":2063.3,"products":{"REDMI Buds 8 青春版":{"orders":1,"revenue":116.0,"avg_price":0},"REDMI Watch 6":{"orders":1,"revenue":483.3,"avg_price":0},"小米手环10":{"orders":1,"revenue":269.0,"avg_price":0},"小米手环10 Pro":{"orders":3,"revenue":1195.0,"avg_price":0}}},"3":{"orders":3,"revenue":935.0,"products":{"小米手环10":{"orders":2,"revenue":536.0,"avg_price":0},"小米手环10 Pro":{"orders":1,"revenue":399.0,"avg_price":0}}},"4":{"orders":4,"revenue":1313.0,"products":{"REDMI Watch 6":{"orders":1,"revenue":537.0,"avg_price":0},"小米手环10":{"orders":3,"revenue":776.0,"avg_price":0}}},"5":{"orders":4,"revenue":1125.15,"products":{"小米手环10":{"orders":3,"revenue":786.0,"avg_price":0},"小米手环10 Pro":{"orders":1,"revenue":339.15,"avg_price":0}}},"6":{"orders":4,"revenue":1089.61,"products":{"【新品】XiaomiTagBLE版本定位追踪器防丢":{"orders":1,"revenue":32.72,"avg_price":0},"小米手环10":{"orders":1,"revenue":269.0,"avg_price":0},"小米手环10 Pro":{"orders":2,"revenue":787.89,"avg_price":0}}},"7":{"orders":15,"revenue":4757.0,"products":{"REDMI Watch 6":{"orders":1,"revenue":520.0,"avg_price":0},"小米手环10":{"orders":11,"revenue":3043.0,"avg_price":0},"小米手环10 Pro":{"orders":3,"revenue":1194.0,"avg_price":0}}},"8":{"orders":9,"revenue":3574.6,"products":{"REDMI Watch 6":{"orders":3,"revenue":1563.2,"avg_price":0},"小米手环10":{"orders":4,"revenue":1286.0,"avg_price":0},"小米手环10 Pro":{"orders":2,"revenue":725.4,"avg_price":0}}},"9":{"orders":25,"revenue":9088.68,"products":{"REDMI Watch 6":{"orders":2,"revenue":1076.0,"avg_price":0},"【新品】XiaomiTagBLE版本定位追踪器防丢":{"orders":1,"revenue":32.0,"avg_price":0},"小米手环10":{"orders":6,"revenue":1844.0,"avg_price":0},"小米手环10 Pro":{"orders":16,"revenue":6136.68,"avg_price":0}}},"10":{"orders":13,"revenue":4962.0,"products":{"小米手环10":{"orders":3,"revenue":1012.0,"avg_price":0},"小米手环10 Pro":{"orders":10,"revenue":3950.0,"avg_price":0}}},"11":{"orders":17,"revenue":6396.75,"products":{"小米手环10":{"orders":5,"revenue":1653.0,"avg_price":0},"小米手环10 Pro":{"orders":12,"revenue":4743.75,"avg_price":0}}},"12":{"orders":12,"revenue":5281.0,"products":{"REDMI Watch 6":{"orders":1,"revenue":539.0,"avg_price":0},"小米手环10":{"orders":1,"revenue":307.0,"avg_price":0},"小米手环10 Pro":{"orders":10,"revenue":4435.0,"avg_price":0}}},"13":{"orders":16,"revenue":5692.54,"products":{"小米手环10":{"orders":6,"revenue":1762.0,"avg_price":0},"小米手环10 Pro":{"orders":10,"revenue":3930.54,"avg_price":0}}},"14":{"orders":25,"revenue":9734.32,"products":{"REDMI Watch 6":{"orders":2,"revenue":1022.4,"avg_price":0},"小米手环10":{"orders":6,"revenue":1709.92,"avg_price":0},"小米手环10 Pro":{"orders":17,"revenue":7002.0,"avg_price":0}}},"15":{"orders":19,"revenue":7335.45,"products":{"REDMI Buds 8 Pro":{"orders":1,"revenue":374.0,"avg_price":0},"REDMI Watch 6":{"orders":4,"revenue":2048.3,"avg_price":0},"小米手环10":{"orders":6,"revenue":1834.0,"avg_price":0},"小米手环10 Pro":{"orders":8,"revenue":3079.15,"avg_price":0}}},"16":{"orders":5,"revenue":1915.85,"products":{"REDMI Watch 6":{"orders":1,"revenue":479.7,"avg_price":0},"小米手环10":{"orders":2,"revenue":698.0,"avg_price":0},"小米手环10 Pro":{"orders":2,"revenue":738.15,"avg_price":0}}},"17":{"orders":13,"revenue":4411.21,"products":{"REDMI Buds 8 活力版":{"orders":1,"revenue":81.06,"avg_price":0},"小米手环10":{"orders":5,"revenue":1597.0,"avg_price":0},"小米手环10 Pro":{"orders":7,"revenue":2733.15,"avg_price":0}}},"18":{"orders":13,"revenue":5189.65,"products":{"小米手环10":{"orders":2,"revenue":754.0,"avg_price":0},"小米手环10 Pro":{"orders":11,"revenue":4435.65,"avg_price":0}}},"19":{"orders":19,"revenue":6658.95,"products":{"小米手环10":{"orders":7,"revenue":1913.0,"avg_price":0},"小米手环10 Pro":{"orders":12,"revenue":4745.95,"avg_price":0}}},"20":{"orders":18,"revenue":7177.5,"products":{"REDMI Watch 6":{"orders":5,"revenue":2641.1,"avg_price":0},"小米手环10":{"orders":5,"revenue":1555.0,"avg_price":0},"小米手环10 Pro":{"orders":8,"revenue":2981.4,"avg_price":0}}},"21":{"orders":28,"revenue":9867.06,"products":{"REDMI 手环 3":{"orders":1,"revenue":139.0,"avg_price":0},"小米手环10":{"orders":14,"revenue":4630.0,"avg_price":0},"小米手环10 Pro":{"orders":13,"revenue":5098.06,"avg_price":0}}},"22":{"orders":14,"revenue":4815.4,"products":{"REDMI Watch 6":{"orders":1,"revenue":522.0,"avg_price":0},"小米手环10":{"orders":8,"revenue":2300.4,"avg_price":0},"小米手环10 Pro":{"orders":5,"revenue":1993.0,"avg_price":0}}},"23":{"orders":16,"revenue":5832.2,"products":{"REDMI Watch 6":{"orders":3,"revenue":1509.2,"avg_price":0},"小米手环10":{"orders":9,"revenue":2697.0,"avg_price":0},"小米手环10 Pro":{"orders":4,"revenue":1626.0,"avg_price":0}}}}},"小米官方手表":{"_hourly_stats":{"0":{"orders":9,"revenue":3732.1,"products":{"REDMI Watch 6":{"orders":5,"revenue":2701.1,"avg_price":0},"小米手环10":{"orders":4,"revenue":1031.0,"avg_price":0}}},"1":{"orders":6,"revenue":2877.1,"products":{"REDMI Watch 6":{"orders":5,"revenue":2628.1,"avg_price":0},"小米手环10":{"orders":1,"revenue":249.0,"avg_price":0}}},"2":{"orders":6,"revenue":4124.5,"products":{"REDMI Watch 6":{"orders":5,"revenue":2425.5,"avg_price":0},"小米AI眼镜":{"orders":1,"revenue":1699.0,"avg_price":0}}},"3":{"orders":3,"revenue":1417.0,"products":{"REDMI Watch 6":{"orders":1,"revenue":539.0,"avg_price":0},"小米手环10 Pro":{"orders":2,"revenue":878.0,"avg_price":0}}},"4":{"orders":3,"revenue":1507.4,"products":{"REDMI Watch 6":{"orders":3,"revenue":1507.4,"avg_price":0}}},"5":{"orders":3,"revenue":1343.0,"products":{"REDMI Watch 6":{"orders":2,"revenue":1074.0,"avg_price":0},"小米手环10":{"orders":1,"revenue":269.0,"avg_price":0}}},"6":{"orders":2,"revenue":908.0,"products":{"REDMI Watch 6":{"orders":1,"revenue":529.0,"avg_price":0},"小米手环10":{"orders":1,"revenue":379.0,"avg_price":0}}},"7":{"orders":2,"revenue":750.05,"products":{"REDMI Watch 6":{"orders":1,"revenue":512.05,"avg_price":0},"小米手环10":{"orders":1,"revenue":238.0,"avg_price":0}}},"8":{"orders":10,"revenue":4557.0,"products":{"REDMI Watch 6":{"orders":6,"revenue":2924.0,"avg_price":0},"小米手环10 Pro":{"orders":4,"revenue":1633.0,"avg_price":0}}},"9":{"orders":14,"revenue":6083.76,"products":{"REDMI Watch 6":{"orders":8,"revenue":4254.1,"avg_price":0},"小米手环10":{"orders":4,"revenue":1180.0,"avg_price":295.0},"小米手环10 Pro":{"orders":2,"revenue":649.66,"avg_price":0}}},"10":{"orders":10,"revenue":4854.3,"products":{"REDMI Watch 6":{"orders":9,"revenue":4535.3,"avg_price":0},"小米手环10":{"orders":1,"revenue":319.0,"avg_price":0}}},"11":{"orders":10,"revenue":4809.1,"products":{"REDMI Watch 6":{"orders":7,"revenue":3697.1,"avg_price":0},"小米手环10":{"orders":1,"revenue":316.0,"avg_price":0},"小米手环10 Pro":{"orders":2,"revenue":796.0,"avg_price":0}}},"12":{"orders":4,"revenue":2133.0,"products":{"REDMI Watch 6":{"orders":4,"revenue":2133.0,"avg_price":0}}},"13":{"orders":5,"revenue":2385.0,"products":{"REDMI Watch 6":{"orders":3,"revenue":1617.0,"avg_price":0},"小米手环10 Pro":{"orders":2,"revenue":768.0,"avg_price":0}}},"14":{"orders":8,"revenue":4149.0,"products":{"REDMI Watch 6":{"orders":7,"revenue":3763.0,"avg_price":0},"小米手环10 Pro":{"orders":1,"revenue":386.0,"avg_price":0}}},"15":{"orders":14,"revenue":6983.48,"products":{"REDMI Watch 6":{"orders":12,"revenue":6276.48,"avg_price":0},"小米手环10":{"orders":1,"revenue":308.0,"avg_price":0},"小米手环10 Pro":{"orders":1,"revenue":399.0,"avg_price":0}}},"16":{"orders":12,"revenue":5537.38,"products":{"REDMI Watch 6":{"orders":8,"revenue":4299.0,"avg_price":0},"小米手环10":{"orders":3,"revenue":839.38,"avg_price":0},"小米手环10 Pro":{"orders":1,"revenue":399.0,"avg_price":0}}},"17":{"orders":2,"revenue":1078.0,"products":{"REDMI Watch 6":{"orders":2,"revenue":1078.0,"avg_price":0}}},"18":{"orders":8,"revenue":5038.05,"products":{"REDMI Watch 6":{"orders":5,"revenue":2639.0,"avg_price":0},"小米AI眼镜":{"orders":1,"revenue":1697.0,"avg_price":0},"小米手环10":{"orders":1,"revenue":303.05,"avg_price":0},"小米手环10 Pro":{"orders":1,"revenue":399.0,"avg_price":0}}},"19":{"orders":8,"revenue":4066.6,"products":{"REDMI Watch 6":{"orders":7,"revenue":3770.0,"avg_price":0},"小米手环10":{"orders":1,"revenue":296.6,"avg_price":0}}},"20":{"orders":9,"revenue":4342.0,"products":{"REDMI Watch 6":{"orders":7,"revenue":3771.0,"avg_price":0},"小米手环10":{"orders":2,"revenue":571.0,"avg_price":0}}},"21":{"orders":11,"revenue":5334.0,"products":{"REDMI Watch 6":{"orders":9,"revenue":4796.0,"avg_price":0},"小米手环10 Pro":{"orders":1,"revenue":399.0,"avg_price":0},"耳机配件":{"orders":1,"revenue":139.0,"avg_price":0}}},"22":{"orders":9,"revenue":4830.0,"products":{"REDMI Watch 6":{"orders":9,"revenue":4830.0,"avg_price":0}}},"23":{"orders":3,"revenue":1477.0,"products":{"REDMI Watch 6":{"orders":2,"revenue":1078.0,"avg_price":0},"小米手环10 Pro":{"orders":1,"revenue":399.0,"avg_price":0}}}}},"小米官方手表直播号":{"_hourly_stats":{"14":{"orders":2,"revenue":1024.1,"products":{"REDMI Watch 6":{"orders":2,"revenue":1024.1,"avg_price":0}}},"15":{"orders":6,"revenue":1986.04,"products":{"REDMI Watch 6":{"orders":2,"revenue":1078.0,"avg_price":0},"小米手环10":{"orders":4,"revenue":908.04,"avg_price":0}}},"16":{"orders":3,"revenue":1062.1,"products":{"REDMI Watch 6":{"orders":1,"revenue":485.1,"avg_price":0},"小米手环10":{"orders":1,"revenue":238.0,"avg_price":0},"小米手环10 Pro":{"orders":1,"revenue":339.0,"avg_price":0}}},"18":{"orders":1,"revenue":485.1,"products":{"REDMI Watch 6":{"orders":1,"revenue":485.1,"avg_price":0}}},"19":{"orders":2,"revenue":624.1,"products":{"REDMI Watch 6":{"orders":1,"revenue":485.1,"avg_price":0},"耳机配件":{"orders":1,"revenue":139.0,"avg_price":0}}},"20":{"orders":1,"revenue":539.0,"products":{"REDMI Watch 6":{"orders":1,"revenue":539.0,"avg_price":0}}},"22":{"orders":4,"revenue":1805.85,"products":{"REDMI Watch 6":{"orders":3,"revenue":1509.2,"avg_price":0},"小米手环10 Pro":{"orders":1,"revenue":296.65,"avg_price":0}}}}},"小米官方耳机直播间":{"_hourly_stats":{"9":{"orders":3,"revenue":2333.0,"products":{"Xiaomi 开放式耳机":{"orders":3,"revenue":2333.0,"avg_price":0}}},"10":{"orders":6,"revenue":3929.99,"products":{"REDMI Buds 8 青春版":{"orders":1,"revenue":129.0,"avg_price":0},"Xiaomi 开放式耳机":{"orders":5,"revenue":3800.99,"avg_price":0}}},"11":{"orders":2,"revenue":1567.0,"products":{"Xiaomi 开放式耳机":{"orders":2,"revenue":1567.0,"avg_price":0}}},"12":{"orders":3,"revenue":2308.0,"products":{"Xiaomi 开放式耳机":{"orders":3,"revenue":2308.0,"avg_price":0}}},"13":{"orders":4,"revenue":1597.0,"products":{"REDMI Buds 8 活力版":{"orders":1,"revenue":71.0,"avg_price":0},"REDMI Buds 8 青春版":{"orders":1,"revenue":92.0,"avg_price":0},"Xiaomi Buds 6":{"orders":1,"revenue":635.0,"avg_price":0},"Xiaomi 开放式耳机":{"orders":1,"revenue":799.0,"avg_price":0}}},"14":{"orders":3,"revenue":2386.71,"products":{"Xiaomi 开放式耳机":{"orders":3,"revenue":2386.71,"avg_price":0}}},"15":{"orders":3,"revenue":1692.0,"products":{"REDMI Buds 8 青春版":{"orders":1,"revenue":139.0,"avg_price":0},"Xiaomi 开放式耳机":{"orders":2,"revenue":1553.0,"avg_price":0}}},"16":{"orders":1,"revenue":797.0,"products":{"Xiaomi 开放式耳机":{"orders":1,"revenue":797.0,"avg_price":0}}},"17":{"orders":4,"revenue":3115.0,"products":{"Xiaomi 开放式耳机":{"orders":4,"revenue":3115.0,"avg_price":0}}},"18":{"orders":2,"revenue":1530.0,"products":{"Xiaomi 开放式耳机":{"orders":2,"revenue":1530.0,"avg_price":0}}},"19":{"orders":6,"revenue":4682.0,"products":{"Xiaomi 开放式耳机":{"orders":6,"revenue":4682.0,"avg_price":0}}},"20":{"orders":6,"revenue":4046.0,"products":{"REDMI Buds 8 青春版":{"orders":1,"revenue":139.0,"avg_price":0},"Xiaomi 开放式耳机":{"orders":5,"revenue":3907.0,"avg_price":0}}},"21":{"orders":5,"revenue":2439.0,"products":{"Xiaomi 开放式耳机":{"orders":3,"revenue":2397.0,"avg_price":0},"小米小背包 10L -亮蓝色-(19508)":{"orders":1,"revenue":21.0,"avg_price":0},"小米小背包 10L -黄色-(19512)":{"orders":1,"revenue":21.0,"avg_price":0}}},"22":{"orders":1,"revenue":799.0,"products":{"Xiaomi 开放式耳机":{"orders":1,"revenue":799.0,"avg_price":0}}},"23":{"orders":2,"revenue":1579.0,"products":{"Xiaomi 开放式耳机":{"orders":2,"revenue":1579.0,"avg_price":0}}}}},"小米手环":{"_hourly_stats":{"0":{"orders":29,"revenue":8954.5,"products":{"充电配件":{"orders":1,"revenue":19.9,"avg_price":0},"小米手环10":{"orders":14,"revenue":3612.0,"avg_price":0},"小米手环10 Pro":{"orders":14,"revenue":5322.6,"avg_price":0}}},"1":{"orders":12,"revenue":3783.3,"products":{"REDMI Buds 8 活力版":{"orders":1,"revenue":72.0,"avg_price":0},"小米手环10":{"orders":5,"revenue":1360.0,"avg_price":0},"小米手环10 Pro":{"orders":6,"revenue":2351.3,"avg_price":0}}},"2":{"orders":13,"revenue":4687.1,"products":{"REDMI Watch 6":{"orders":1,"revenue":485.1,"avg_price":0},"小米手环10":{"orders":4,"revenue":1012.0,"avg_price":0},"小米手环10 Pro":{"orders":8,"revenue":3190.0,"avg_price":0}}},"3":{"orders":7,"revenue":2725.15,"products":{"REDMI Watch 6":{"orders":1,"revenue":539.0,"avg_price":0},"小米手环10":{"orders":1,"revenue":269.0,"avg_price":0},"小米手环10 Pro":{"orders":5,"revenue":1917.15,"avg_price":0}}},"7":{"orders":13,"revenue":2746.57,"products":{"REDMI Buds 8 活力版":{"orders":1,"revenue":73.88,"avg_price":0},"充电配件":{"orders":1,"revenue":15.9,"avg_price":0},"小米手环10":{"orders":7,"revenue":1896.43,"avg_price":0},"小米手环10 Pro":{"orders":2,"revenue":729.63,"avg_price":0},"插线板/配件":{"orders":2,"revenue":30.73,"avg_price":0}}},"8":{"orders":15,"revenue":5819.6,"products":{"REDMI Watch 6":{"orders":1,"revenue":539.0,"avg_price":0},"小米手环10 Pro":{"orders":14,"revenue":5280.6,"avg_price":0}}},"9":{"orders":52,"revenue":18655.32,"products":{"REDMI Buds 8 活力版":{"orders":1,"revenue":73.0,"avg_price":0},"REDMI Watch 6":{"orders":2,"revenue":1064.0,"avg_price":0},"充电配件":{"orders":1,"revenue":19.9,"avg_price":0},"小米手环10":{"orders":11,"revenue":3017.14,"avg_price":0},"小米手环10 Pro":{"orders":37,"revenue":14481.28,"avg_price":0}}},"10":{"orders":42,"revenue":15518.69,"products":{"REDMI Buds 8 活力版":{"orders":2,"revenue":144.37,"avg_price":0},"REDMI Watch 6":{"orders":1,"revenue":539.0,"avg_price":0},"小米手环10":{"orders":2,"revenue":688.0,"avg_price":0},"小米手环10 Pro":{"orders":37,"revenue":14147.32,"avg_price":0}}},"11":{"orders":34,"revenue":12326.53,"products":{"REDMI Buds 8 活力版":{"orders":1,"revenue":74.0,"avg_price":0},"小米手环10":{"orders":3,"revenue":712.33,"avg_price":0},"小米手环10 Pro":{"orders":30,"revenue":11540.2,"avg_price":0}}},"12":{"orders":33,"revenue":11493.25,"products":{"REDMI Buds 6 活力版":{"orders":1,"revenue":64.0,"avg_price":0},"REDMI Buds 8 Pro":{"orders":1,"revenue":374.0,"avg_price":0},"REDMI Buds 8 活力版":{"orders":1,"revenue":70.0,"avg_price":0},"小米手环10":{"orders":9,"revenue":2731.0,"avg_price":0},"小米手环10 Pro":{"orders":21,"revenue":8254.25,"avg_price":0}}},"13":{"orders":27,"revenue":9685.43,"products":{"REDMI Watch 6":{"orders":1,"revenue":485.1,"avg_price":0},"小米手环10":{"orders":7,"revenue":1718.78,"avg_price":0},"小米手环10 Pro":{"orders":19,"revenue":7481.55,"avg_price":0}}},"14":{"orders":27,"revenue":9382.78,"products":{"REDMI Buds 6 活力版":{"orders":1,"revenue":44.8,"avg_price":0},"小米手环10":{"orders":8,"revenue":2459.05,"avg_price":0},"小米手环10 Pro":{"orders":18,"revenue":6878.93,"avg_price":0}}},"15":{"orders":26,"revenue":10020.99,"products":{"REDMI Buds 8 青春版":{"orders":1,"revenue":139.0,"avg_price":0},"REDMI Watch 6":{"orders":2,"revenue":1028.0,"avg_price":0},"小米手环10":{"orders":4,"revenue":1249.0,"avg_price":0},"小米手环10 Pro":{"orders":19,"revenue":7604.99,"avg_price":0}}},"16":{"orders":24,"revenue":8498.25,"products":{"REDMI Watch 6":{"orders":2,"revenue":1065.0,"avg_price":0},"充电配件":{"orders":1,"revenue":19.9,"avg_price":0},"小米手环10":{"orders":4,"revenue":1176.0,"avg_price":0},"小米手环10 Pro":{"orders":16,"revenue":6212.45,"avg_price":0},"插线板/配件":{"orders":1,"revenue":24.9,"avg_price":0}}},"17":{"orders":25,"revenue":9626.63,"products":{"REDMI Watch 6":{"orders":1,"revenue":539.0,"avg_price":0},"小米手环10":{"orders":4,"revenue":1310.47,"avg_price":0},"小米手环10 Pro":{"orders":20,"revenue":7777.16,"avg_price":0}}},"18":{"orders":16,"revenue":5991.45,"products":{"REDMI Watch 6":{"orders":1,"revenue":489.0,"avg_price":0},"小米手环10":{"orders":4,"revenue":1242.0,"avg_price":0},"小米手环10 Pro":{"orders":11,"revenue":4260.45,"avg_price":0}}},"19":{"orders":29,"revenue":10583.81,"products":{"REDMI Buds 8 活力版":{"orders":1,"revenue":79.0,"avg_price":0},"REDMI Buds 8 青春版":{"orders":1,"revenue":108.0,"avg_price":0},"REDMI Watch 6":{"orders":2,"revenue":1078.0,"avg_price":0},"小米手环10":{"orders":7,"revenue":2341.0,"avg_price":334.43},"小米手环10 Pro":{"orders":17,"revenue":6653.81,"avg_price":0},"小米手环9 Pro":{"orders":1,"revenue":324.0,"avg_price":0}}},"20":{"orders":35,"revenue":13553.02,"products":{"REDMI Watch 6":{"orders":1,"revenue":539.0,"avg_price":0},"小米手环10":{"orders":7,"revenue":2309.65,"avg_price":0},"小米手环10 Pro":{"orders":27,"revenue":10704.37,"avg_price":0}}},"21":{"orders":36,"revenue":13335.03,"products":{"REDMI Buds 8 活力版":{"orders":1,"revenue":82.93,"avg_price":0},"REDMI Watch 6":{"orders":1,"revenue":539.0,"avg_price":0},"小米手环10":{"orders":4,"revenue":1255.0,"avg_price":0},"小米手环10 Pro":{"orders":29,"revenue":11433.2,"avg_price":0},"插线板/配件":{"orders":1,"revenue":24.9,"avg_price":0}}},"22":{"orders":23,"revenue":8114.77,"products":{"REDMI Buds 8 活力版":{"orders":1,"revenue":76.0,"avg_price":0},"小米手环10":{"orders":5,"revenue":1480.45,"avg_price":0},"小米手环10 Pro":{"orders":17,"revenue":6558.32,"avg_price":0}}},"23":{"orders":28,"revenue":10579.19,"products":{"REDMI Buds 8 活力版":{"orders":1,"revenue":78.0,"avg_price":0},"REDMI Watch 6":{"orders":4,"revenue":1999.6,"avg_price":0},"小米手环10":{"orders":3,"revenue":874.97,"avg_price":0},"小米手环10 Pro":{"orders":19,"revenue":7342.62,"avg_price":0},"小米手环9 Pro":{"orders":1,"revenue":284.0,"avg_price":0}}}}},"小米手表":{"_hourly_stats":{"6":{"orders":1,"revenue":1239.0,"products":{"【平台活动】小米手表 Xiaomi Watch S":{"orders":1,"revenue":1239.0,"avg_price":0}}},"18":{"orders":2,"revenue":628.09,"products":{"小米手环10 Pro":{"orders":2,"revenue":628.09,"avg_price":0}}},"19":{"orders":3,"revenue":3117.0,"products":{"【加黑链接】小米手表 Xiaomi Watch S":{"orders":3,"revenue":3117.0,"avg_price":0}}},"20":{"orders":3,"revenue":1247.0,"products":{"REDMI Watch 6":{"orders":2,"revenue":1018.0,"avg_price":0},"小米手环10":{"orders":1,"revenue":229.0,"avg_price":0}}},"21":{"orders":5,"revenue":3567.0,"products":{"【加黑链接】小米手表 Xiaomi Watch S":{"orders":3,"revenue":3117.0,"avg_price":0},"小米手环10":{"orders":2,"revenue":450.0,"avg_price":0}}},"22":{"orders":1,"revenue":935.1,"products":{"【平台自营】小米手表 Xiaomi Watch S":{"orders":1,"revenue":935.1,"avg_price":0}}},"23":{"orders":1,"revenue":485.1,"products":{"REDMI Watch 6":{"orders":1,"revenue":485.1,"avg_price":0}}}}},"小米手表官旗直播间":{"_hourly_stats":{"0":{"orders":27,"revenue":7508.62,"products":{"REDMI Watch 6":{"orders":2,"revenue":973.1,"avg_price":0},"【新品】Xiaomi Tag 智能定位 适配澎湃 ":{"orders":4,"revenue":137.78,"avg_price":0},"【自营】Xiaomi Watch S5 时尚新品智":{"orders":2,"revenue":1922.15,"avg_price":0},"小米手环10":{"orders":19,"revenue":4475.59,"avg_price":0}}},"1":{"orders":1,"revenue":1039.0,"products":{"【平台活动】小米手表 Xiaomi Watch S":{"orders":1,"revenue":1039.0,"avg_price":0}}},"7":{"orders":3,"revenue":491.48,"products":{"【新品】Xiaomi Tag 智能定位 适配澎湃 ":{"orders":1,"revenue":35.0,"avg_price":0},"小米手环10":{"orders":2,"revenue":456.48,"avg_price":0}}},"9":{"orders":2,"revenue":2103.6,"products":{"【平台活动】小米手表 Xiaomi Watch S":{"orders":1,"revenue":1223.0,"avg_price":0},"【自营】Xiaomi Watch S5 时尚新品智":{"orders":1,"revenue":880.6,"avg_price":0}}},"10":{"orders":1,"revenue":1002.0,"products":{"【自营】Xiaomi Watch S5 时尚新品智":{"orders":1,"revenue":1002.0,"avg_price":0}}},"11":{"orders":8,"revenue":6231.71,"products":{"REDMI Watch 6":{"orders":1,"revenue":529.0,"avg_price":0},"【平台活动】小米手表 Xiaomi Watch S":{"orders":4,"revenue":4154.0,"avg_price":0},"【平台自营】小米手表 Xiaomi Watch S":{"orders":1,"revenue":1077.93,"avg_price":0},"小米手环10":{"orders":2,"revenue":470.78,"avg_price":0}}},"12":{"orders":3,"revenue":1023.0,"products":{"REDMI Watch 6":{"orders":1,"revenue":515.0,"avg_price":0},"小米手环10":{"orders":2,"revenue":508.0,"avg_price":0}}},"15":{"orders":1,"revenue":1077.93,"products":{"【平台自营】小米手表 Xiaomi Watch S":{"orders":1,"revenue":1077.93,"avg_price":0}}}}},"小米数码旗舰店":{"_hourly_stats":{"0":{"orders":36,"revenue":9647.23,"products":{"REDMI Watch 6":{"orders":1,"revenue":441.0,"avg_price":0},"小米手环10":{"orders":33,"revenue":8411.23,"avg_price":0},"小米手环10 Pro":{"orders":2,"revenue":795.0,"avg_price":0}}},"1":{"orders":30,"revenue":9433.67,"products":{"REDMI Buds 8 活力版":{"orders":1,"revenue":81.0,"avg_price":0},"Xiaomi 开放式耳机":{"orders":1,"revenue":699.0,"avg_price":0},"小米手环10":{"orders":19,"revenue":5132.67,"avg_price":0},"小米手环10 Pro":{"orders":9,"revenue":3521.0,"avg_price":0}}},"2":{"orders":11,"revenue":2828.6,"products":{"【新品】XiaomiTagBLE版本定位追踪器防丢":{"orders":1,"revenue":35.6,"avg_price":0},"小米手环10":{"orders":8,"revenue":2034.0,"avg_price":0},"小米手环10 Pro":{"orders":2,"revenue":759.0,"avg_price":0}}},"3":{"orders":12,"revenue":4996.7,"products":{"REDMI Watch 6":{"orders":3,"revenue":1455.6,"avg_price":0},"【自营平台】XIaomI Watch S5 新品手":{"orders":1,"revenue":1169.1,"avg_price":0},"小米手环10":{"orders":5,"revenue":1245.0,"avg_price":0},"小米手环10 Pro":{"orders":2,"revenue":798.0,"avg_price":0},"小米手环9 Pro":{"orders":1,"revenue":329.0,"avg_price":0}}},"4":{"orders":6,"revenue":2230.62,"products":{"REDMI Watch 6":{"orders":1,"revenue":485.1,"avg_price":0},"小米手环10":{"orders":2,"revenue":543.37,"avg_price":0},"小米手环10 Pro":{"orders":3,"revenue":1202.15,"avg_price":0}}},"5":{"orders":5,"revenue":1583.15,"products":{"小米手环10":{"orders":3,"revenue":845.0,"avg_price":0},"小米手环10 Pro":{"orders":2,"revenue":738.15,"avg_price":0}}},"6":{"orders":6,"revenue":1390.7,"products":{"【新品】XiaomiTagBLE版本定位追踪器防丢":{"orders":1,"revenue":28.7,"avg_price":0},"小米手环10":{"orders":5,"revenue":1362.0,"avg_price":0}}},"7":{"orders":15,"revenue":4479.8,"products":{"REDMI Watch 6":{"orders":1,"revenue":477.0,"avg_price":0},"小米手环10":{"orders":12,"revenue":3128.8,"avg_price":0},"小米手环10 Pro":{"orders":2,"revenue":874.0,"avg_price":0}}},"8":{"orders":7,"revenue":1895.0,"products":{"【新品】XiaomiTagBLE版本定位追踪器防丢":{"orders":1,"revenue":27.0,"avg_price":0},"小米手环10":{"orders":4,"revenue":1072.0,"avg_price":0},"小米手环10 Pro":{"orders":2,"revenue":796.0,"avg_price":0}}},"9":{"orders":1,"revenue":317.0,"products":{"小米手环10":{"orders":1,"revenue":317.0,"avg_price":0}}},"10":{"orders":3,"revenue":1047.0,"products":{"小米手环10":{"orders":2,"revenue":648.0,"avg_price":0},"小米手环10 Pro":{"orders":1,"revenue":399.0,"avg_price":0}}},"11":{"orders":9,"revenue":3187.0,"products":{"小米手环10":{"orders":5,"revenue":1591.0,"avg_price":318.2},"小米手环10 Pro":{"orders":3,"revenue":1267.0,"avg_price":0},"小米手环9 Pro":{"orders":1,"revenue":329.0,"avg_price":0}}},"12":{"orders":17,"revenue":5613.83,"products":{"REDMI Buds 8 活力版":{"orders":1,"revenue":69.83,"avg_price":0},"REDMI Watch 6":{"orders":2,"revenue":1030.0,"avg_price":0},"小米手环10":{"orders":9,"revenue":2552.0,"avg_price":0},"小米手环10 Pro":{"orders":4,"revenue":1638.0,"avg_price":0},"小米手环9 Pro":{"orders":1,"revenue":324.0,"avg_price":0}}},"13":{"orders":13,"revenue":5284.54,"products":{"Xiaomi 开放式耳机":{"orders":1,"revenue":799.0,"avg_price":0},"小米手环10":{"orders":1,"revenue":255.55,"avg_price":0},"小米手环10 Pro":{"orders":11,"revenue":4229.99,"avg_price":0}}},"14":{"orders":10,"revenue":3636.0,"products":{"小米手环10":{"orders":4,"revenue":1158.0,"avg_price":0},"小米手环10 Pro":{"orders":6,"revenue":2478.0,"avg_price":0}}},"15":{"orders":12,"revenue":3984.85,"products":{"REDMI Watch 6":{"orders":2,"revenue":945.9,"avg_price":0},"小米手环10":{"orders":8,"revenue":2342.0,"avg_price":0},"小米手环10 Pro":{"orders":2,"revenue":696.95,"avg_price":0}}},"16":{"orders":13,"revenue":5001.86,"products":{"REDMI Watch 6":{"orders":2,"revenue":1011.2,"avg_price":0},"小米手环10":{"orders":5,"revenue":1639.0,"avg_price":0},"小米手环10 Pro":{"orders":6,"revenue":2351.66,"avg_price":0}}},"17":{"orders":13,"revenue":4339.1,"products":{"REDMI Watch 6":{"orders":1,"revenue":485.1,"avg_price":0},"小米手环10":{"orders":8,"revenue":2298.0,"avg_price":0},"小米手环10 Pro":{"orders":4,"revenue":1556.0,"avg_price":0}}},"18":{"orders":8,"revenue":2750.0,"products":{"小米手环10":{"orders":5,"revenue":1555.0,"avg_price":0},"小米手环10 Pro":{"orders":3,"revenue":1195.0,"avg_price":0}}},"19":{"orders":10,"revenue":3642.45,"products":{"REDMI Watch 6":{"orders":1,"revenue":456.3,"avg_price":0},"小米手环10":{"orders":3,"revenue":967.0,"avg_price":0},"小米手环10 Pro":{"orders":6,"revenue":2219.15,"avg_price":0}}},"20":{"orders":10,"revenue":3832.62,"products":{"REDMI Watch 6":{"orders":2,"revenue":970.2,"avg_price":0},"小米手环10":{"orders":4,"revenue":1361.0,"avg_price":0},"小米手环10 Pro":{"orders":4,"revenue":1501.42,"avg_price":0}}},"21":{"orders":7,"revenue":2703.04,"products":{"REDMI Watch 6":{"orders":1,"revenue":539.0,"avg_price":0},"小米手环10":{"orders":1,"revenue":259.0,"avg_price":0},"小米手环10 Pro":{"orders":5,"revenue":1905.04,"avg_price":0}}},"22":{"orders":10,"revenue":4313.37,"products":{"Xiaomi 开放式耳机":{"orders":2,"revenue":1526.0,"avg_price":0},"小米手环10":{"orders":1,"revenue":319.0,"avg_price":0},"小米手环10 Pro":{"orders":6,"revenue":2139.37,"avg_price":0},"小米手环9 Pro":{"orders":1,"revenue":329.0,"avg_price":0}}},"23":{"orders":3,"revenue":1150.0,"products":{"小米手环10":{"orders":2,"revenue":754.0,"avg_price":377.0},"小米手环10 Pro":{"orders":1,"revenue":396.0,"avg_price":0}}}}},"小米数码智能旗舰店":{"_hourly_stats":{"0":{"orders":8,"revenue":2274.71,"products":{"小米手环10":{"orders":6,"revenue":1553.56,"avg_price":0},"小米手环10 Pro":{"orders":2,"revenue":721.15,"avg_price":0}}},"1":{"orders":4,"revenue":1196.0,"products":{"小米手环10":{"orders":3,"revenue":797.0,"avg_price":0},"小米手环10 Pro":{"orders":1,"revenue":399.0,"avg_price":0}}},"2":{"orders":4,"revenue":1396.0,"products":{"REDMI Watch 6":{"orders":1,"revenue":539.0,"avg_price":0},"小米手环10":{"orders":3,"revenue":857.0,"avg_price":0}}},"3":{"orders":2,"revenue":538.0,"products":{"小米手环10":{"orders":2,"revenue":538.0,"avg_price":0}}},"4":{"orders":3,"revenue":1067.0,"products":{"小米手环10":{"orders":1,"revenue":269.0,"avg_price":0},"小米手环10 Pro":{"orders":2,"revenue":798.0,"avg_price":0}}},"6":{"orders":4,"revenue":1466.0,"products":{"小米手环10":{"orders":1,"revenue":269.0,"avg_price":0},"小米手环10 Pro":{"orders":3,"revenue":1197.0,"avg_price":0}}},"7":{"orders":6,"revenue":1756.0,"products":{"小米手环10":{"orders":2,"revenue":548.0,"avg_price":0},"小米手环10 Pro":{"orders":3,"revenue":1166.0,"avg_price":0},"小米水浸卫士2   -默认-(69658)":{"orders":1,"revenue":42.0,"avg_price":0}}},"8":{"orders":5,"revenue":1499.09,"products":{"REDMI Watch 6":{"orders":1,"revenue":485.1,"avg_price":0},"小米手环10":{"orders":1,"revenue":229.0,"avg_price":0},"小米手环10 Pro":{"orders":2,"revenue":747.99,"avg_price":0},"小米水浸卫士2   -默认-(69658)":{"orders":1,"revenue":37.0,"avg_price":0}}},"9":{"orders":19,"revenue":7174.84,"products":{"REDMI Watch 6":{"orders":3,"revenue":1497.5,"avg_price":0},"小米手环10":{"orders":4,"revenue":1009.2,"avg_price":0},"小米手环10 Pro":{"orders":12,"revenue":4668.14,"avg_price":0}}},"10":{"orders":5,"revenue":2015.25,"products":{"REDMI Watch 6":{"orders":1,"revenue":485.1,"avg_price":0},"小米手环10 Pro":{"orders":4,"revenue":1530.15,"avg_price":0}}},"11":{"orders":2,"revenue":627.74,"products":{"小米手环10":{"orders":1,"revenue":269.0,"avg_price":0},"小米手环10 Pro":{"orders":1,"revenue":358.74,"avg_price":0}}},"12":{"orders":7,"revenue":2500.0,"products":{"REDMI Watch 6":{"orders":1,"revenue":539.0,"avg_price":0},"【活动】小米智能摄像机 4C 高清超清3.5K画质":{"orders":1,"revenue":193.0,"avg_price":0},"小米手环10":{"orders":1,"revenue":269.0,"avg_price":0},"小米手环10 Pro":{"orders":4,"revenue":1499.0,"avg_price":0}}},"13":{"orders":5,"revenue":1899.81,"products":{"REDMI Watch 6":{"orders":1,"revenue":485.1,"avg_price":0},"小米手环10":{"orders":2,"revenue":616.71,"avg_price":0},"小米手环10 Pro":{"orders":2,"revenue":798.0,"avg_price":0}}},"14":{"orders":5,"revenue":2021.25,"products":{"REDMI Watch 6":{"orders":1,"revenue":485.1,"avg_price":0},"小米手环10 Pro":{"orders":4,"revenue":1536.15,"avg_price":0}}},"15":{"orders":4,"revenue":1136.9,"products":{"充电配件":{"orders":1,"revenue":19.9,"avg_price":0},"小米手环10":{"orders":1,"revenue":369.0,"avg_price":0},"小米手环10 Pro":{"orders":2,"revenue":748.0,"avg_price":0}}},"16":{"orders":7,"revenue":2270.9,"products":{"充电配件":{"orders":1,"revenue":19.9,"avg_price":0},"小米手环10":{"orders":3,"revenue":1054.0,"avg_price":351.33},"小米手环10 Pro":{"orders":3,"revenue":1197.0,"avg_price":0}}},"17":{"orders":6,"revenue":2221.0,"products":{"小米手环10":{"orders":1,"revenue":269.0,"avg_price":0},"小米手环10 Pro":{"orders":5,"revenue":1952.0,"avg_price":0}}},"18":{"orders":4,"revenue":1403.05,"products":{"小米手环10 Pro":{"orders":3,"revenue":1081.05,"avg_price":0},"小米手环9 Pro":{"orders":1,"revenue":322.0,"avg_price":0}}},"19":{"orders":1,"revenue":399.0,"products":{"小米手环10 Pro":{"orders":1,"revenue":399.0,"avg_price":0}}},"20":{"orders":7,"revenue":2554.94,"products":{"小米手环10 Pro":{"orders":6,"revenue":2175.94,"avg_price":0},"小米手环10":{"orders":1,"revenue":379.0,"avg_price":0}}},"21":{"orders":7,"revenue":2322.11,"products":{"小米手环10":{"orders":2,"revenue":501.0,"avg_price":0},"小米手环10 Pro":{"orders":5,"revenue":1821.11,"avg_price":0}}},"22":{"orders":4,"revenue":1498.77,"products":{"小米手环10 Pro":{"orders":4,"revenue":1498.77,"avg_price":0}}},"23":{"orders":6,"revenue":1941.32,"products":{"小米手环10 Pro":{"orders":6,"revenue":1941.32,"avg_price":0}}}}},"小米智能手表旗舰店":{"_hourly_stats":{"7":{"orders":1,"revenue":22.4,"products":{"【新品上市】 Xiaomi Tag 适配澎湃 OS":{"orders":1,"revenue":22.4,"avg_price":0}}},"8":{"orders":3,"revenue":1935.0,"products":{"REDMI Watch 6":{"orders":1,"revenue":539.0,"avg_price":0},"【平台活动】小米手表 Xiaomi Watch S":{"orders":1,"revenue":1037.0,"avg_price":0},"小米手环10 Pro":{"orders":1,"revenue":359.0,"avg_price":0}}},"9":{"orders":3,"revenue":2161.93,"products":{"【平台活动】小米手表 Xiaomi Watch S":{"orders":2,"revenue":1942.93,"avg_price":0},"小米手环10":{"orders":1,"revenue":219.0,"avg_price":0}}},"10":{"orders":2,"revenue":1202.93,"products":{"【平台活动】小米手表 Xiaomi Watch S":{"orders":1,"revenue":903.93,"avg_price":0},"小米手环10":{"orders":1,"revenue":299.0,"avg_price":0}}},"11":{"orders":7,"revenue":5626.15,"products":{"REDMI Watch 6":{"orders":1,"revenue":539.0,"avg_price":0},"【平台活动】小米手表 Xiaomi Watch S":{"orders":4,"revenue":4420.93,"avg_price":0},"小米手环10 Pro":{"orders":2,"revenue":666.22,"avg_price":0}}},"12":{"orders":4,"revenue":2733.93,"products":{"【平台活动】小米手表 Xiaomi Watch S":{"orders":2,"revenue":2140.93,"avg_price":0},"小米手环10":{"orders":1,"revenue":243.0,"avg_price":0},"小米手环10 Pro":{"orders":1,"revenue":350.0,"avg_price":0}}},"13":{"orders":2,"revenue":1442.93,"products":{"REDMI Watch 6":{"orders":1,"revenue":539.0,"avg_price":0},"【平台活动】小米手表 Xiaomi Watch S":{"orders":1,"revenue":903.93,"avg_price":0}}},"14":{"orders":3,"revenue":729.0,"products":{"【新品上市】 Xiaomi Tag 适配澎湃 OS":{"orders":1,"revenue":32.0,"avg_price":0},"小米手环10":{"orders":1,"revenue":309.0,"avg_price":0},"小米手环10 Pro":{"orders":1,"revenue":388.0,"avg_price":0}}},"15":{"orders":1,"revenue":1039.0,"products":{"【加黑链接】小米手表 Xiaomi Watch S":{"orders":1,"revenue":1039.0,"avg_price":0}}},"19":{"orders":2,"revenue":1578.0,"products":{"REDMI Watch 6":{"orders":1,"revenue":539.0,"avg_price":0},"【加黑链接】小米手表 Xiaomi Watch S":{"orders":1,"revenue":1039.0,"avg_price":0}}},"20":{"orders":3,"revenue":1058.1,"products":{"REDMI Watch 6":{"orders":1,"revenue":485.1,"avg_price":0},"小米手环10":{"orders":2,"revenue":573.0,"avg_price":0}}},"21":{"orders":2,"revenue":1724.1,"products":{"REDMI Watch 6":{"orders":1,"revenue":485.1,"avg_price":0},"【加黑链接】小米手表 Xiaomi Watch S":{"orders":1,"revenue":1239.0,"avg_price":0}}},"22":{"orders":1,"revenue":222.89,"products":{"小米手环10":{"orders":1,"revenue":222.89,"avg_price":0}}},"23":{"orders":1,"revenue":1039.0,"products":{"【加黑链接】小米手表 Xiaomi Watch S":{"orders":1,"revenue":1039.0,"avg_price":0}}}}},"小米智能穿戴国补号":{"_hourly_stats":{"0":{"orders":19,"revenue":6666.5,"products":{"REDMI Watch 6":{"orders":8,"revenue":4202.2,"avg_price":0},"【新品】XiaomiTagBLE版本定位追踪器防丢":{"orders":1,"revenue":27.3,"avg_price":0},"小米手环10":{"orders":10,"revenue":2437.0,"avg_price":0}}},"1":{"orders":22,"revenue":5858.92,"products":{"REDMI Buds 8 活力版":{"orders":1,"revenue":50.25,"avg_price":0},"REDMI Watch 6":{"orders":3,"revenue":1478.2,"avg_price":0},"【新品】XiaomiTagBLE版本定位追踪器防丢":{"orders":1,"revenue":35.0,"avg_price":0},"小米手环10":{"orders":15,"revenue":3549.37,"avg_price":0},"小米手环10 Pro":{"orders":2,"revenue":746.1,"avg_price":0}}},"2":{"orders":7,"revenue":1998.2,"products":{"REDMI Watch 6":{"orders":1,"revenue":475.2,"avg_price":0},"小米手环10":{"orders":5,"revenue":1164.0,"avg_price":0},"小米手环10 Pro":{"orders":1,"revenue":359.0,"avg_price":0}}},"7":{"orders":18,"revenue":5578.01,"products":{"REDMI Watch 6":{"orders":7,"revenue":3417.2,"avg_price":0},"【新品】XiaomiTagBLE版本定位追踪器防丢":{"orders":2,"revenue":56.0,"avg_price":0},"小米手环10":{"orders":8,"revenue":1705.81,"avg_price":0},"小米手环10 Pro":{"orders":1,"revenue":399.0,"avg_price":0}}},"8":{"orders":15,"revenue":6599.28,"products":{"REDMI Watch 6":{"orders":12,"revenue":5912.8,"avg_price":0},"小米手环10":{"orders":3,"revenue":686.48,"avg_price":0}}},"9":{"orders":21,"revenue":9979.73,"products":{"REDMI Buds 8 活力版":{"orders":1,"revenue":81.0,"avg_price":0},"REDMI Watch 6":{"orders":14,"revenue":7021.95,"avg_price":0},"【补贴15%】XIaomI Watch S5 新品":{"orders":1,"revenue":1130.13,"avg_price":0},"小米手环10":{"orders":2,"revenue":685.0,"avg_price":342.5},"小米手环10 Pro":{"orders":3,"revenue":1061.65,"avg_price":0}}},"10":{"orders":19,"revenue":8821.21,"products":{"REDMI Watch 6":{"orders":15,"revenue":7772.1,"avg_price":0},"充电配件":{"orders":1,"revenue":29.9,"avg_price":0},"小米手环10 Pro":{"orders":3,"revenue":1019.21,"avg_price":0}}},"11":{"orders":17,"revenue":8030.4,"products":{"REDMI Watch 6":{"orders":14,"revenue":7205.4,"avg_price":0},"小米手环10":{"orders":2,"revenue":476.0,"avg_price":0},"小米手环10 Pro":{"orders":1,"revenue":349.0,"avg_price":0}}},"12":{"orders":11,"revenue":5859.1,"products":{"REDMI Watch 6":{"orders":11,"revenue":5859.1,"avg_price":0}}},"13":{"orders":7,"revenue":3336.37,"products":{"REDMI Watch 6":{"orders":5,"revenue":2609.1,"avg_price":0},"小米手环10 Pro":{"orders":2,"revenue":727.27,"avg_price":0}}},"14":{"orders":13,"revenue":6489.0,"products":{"REDMI Watch 6":{"orders":10,"revenue":5333.0,"avg_price":0},"小米手环10 Pro":{"orders":3,"revenue":1156.0,"avg_price":0}}},"15":{"orders":8,"revenue":3991.35,"products":{"REDMI Watch 6":{"orders":7,"revenue":3663.4,"avg_price":0},"小米手环10 Pro":{"orders":1,"revenue":327.95,"avg_price":0}}},"16":{"orders":21,"revenue":10058.8,"products":{"REDMI Watch 6":{"orders":18,"revenue":8924.8,"avg_price":0},"小米手环10 Pro":{"orders":3,"revenue":1134.0,"avg_price":0}}},"17":{"orders":15,"revenue":7279.73,"products":{"REDMI Watch 6":{"orders":13,"revenue":6534.99,"avg_price":0},"小米手环10 Pro":{"orders":2,"revenue":744.74,"avg_price":0}}},"18":{"orders":13,"revenue":6204.7,"products":{"REDMI Watch 6":{"orders":12,"revenue":5888.5,"avg_price":0},"小米手环10 Pro":{"orders":1,"revenue":316.2,"avg_price":0}}},"19":{"orders":13,"revenue":5921.7,"products":{"REDMI Watch 6":{"orders":8,"revenue":4148.3,"avg_price":0},"小米手环10":{"orders":1,"revenue":226.0,"avg_price":0},"小米手环10 Pro":{"orders":4,"revenue":1547.4,"avg_price":0}}},"20":{"orders":11,"revenue":5210.47,"products":{"REDMI Watch 6":{"orders":8,"revenue":4180.1,"avg_price":0},"小米手环10":{"orders":1,"revenue":309.0,"avg_price":0},"小米手环10 Pro":{"orders":2,"revenue":721.37,"avg_price":0}}},"21":{"orders":6,"revenue":2514.6,"products":{"REDMI Watch 6":{"orders":5,"revenue":2477.6,"avg_price":0},"【新品】XiaomiTagBLE版本定位追踪器防丢":{"orders":1,"revenue":37.0,"avg_price":0}}},"22":{"orders":4,"revenue":2102.1,"products":{"REDMI Watch 6":{"orders":4,"revenue":2102.1,"avg_price":0}}},"23":{"orders":8,"revenue":4096.4,"products":{"REDMI Watch 6":{"orders":8,"revenue":4096.4,"avg_price":0}}}}},"小米智能穿戴授权号":{"_hourly_stats":{"0":{"orders":14,"revenue":3643.09,"products":{"小米手环10":{"orders":13,"revenue":3303.94,"avg_price":0},"小米手环10 Pro":{"orders":1,"revenue":339.15,"avg_price":0}}},"1":{"orders":15,"revenue":3648.63,"products":{"小米手环10":{"orders":14,"revenue":3309.48,"avg_price":0},"小米手环10 Pro":{"orders":1,"revenue":339.15,"avg_price":0}}},"7":{"orders":11,"revenue":3799.15,"products":{"REDMI Watch 6":{"orders":1,"revenue":539.0,"avg_price":0},"小米手环10":{"orders":5,"revenue":1325.0,"avg_price":0},"小米手环10 Pro":{"orders":5,"revenue":1935.15,"avg_price":0}}},"8":{"orders":10,"revenue":3547.4,"products":{"小米手环10":{"orders":2,"revenue":518.0,"avg_price":0},"小米手环10 Pro":{"orders":8,"revenue":3029.4,"avg_price":0}}},"9":{"orders":23,"revenue":8618.05,"products":{"小米手环10":{"orders":5,"revenue":1641.0,"avg_price":328.2},"小米手环10 Pro":{"orders":18,"revenue":6977.05,"avg_price":0}}},"10":{"orders":21,"revenue":7652.35,"products":{"REDMI Watch 6":{"orders":1,"revenue":485.1,"avg_price":0},"小米手环10":{"orders":5,"revenue":1330.1,"avg_price":0},"小米手环10 Pro":{"orders":15,"revenue":5837.15,"avg_price":0}}},"11":{"orders":19,"revenue":6704.7,"products":{"小米手环10":{"orders":6,"revenue":1622.0,"avg_price":0},"小米手环10 Pro":{"orders":13,"revenue":5082.7,"avg_price":0}}},"12":{"orders":15,"revenue":5358.0,"products":{"REDMI Buds 8 活力版":{"orders":1,"revenue":79.0,"avg_price":0},"小米手环10":{"orders":2,"revenue":574.0,"avg_price":0},"小米手环10 Pro":{"orders":12,"revenue":4705.0,"avg_price":0}}},"13":{"orders":16,"revenue":5851.15,"products":{"小米手环10":{"orders":4,"revenue":1186.0,"avg_price":0},"小米手环10 Pro":{"orders":12,"revenue":4665.15,"avg_price":0}}},"14":{"orders":12,"revenue":4519.5,"products":{"小米手环10":{"orders":2,"revenue":648.0,"avg_price":0},"小米手环10 Pro":{"orders":10,"revenue":3871.5,"avg_price":0}}},"15":{"orders":10,"revenue":3131.25,"products":{"小米手环10":{"orders":7,"revenue":1936.25,"avg_price":0},"小米手环10 Pro":{"orders":3,"revenue":1195.0,"avg_price":0}}},"16":{"orders":11,"revenue":3975.15,"products":{"小米手环10":{"orders":5,"revenue":1652.0,"avg_price":330.4},"小米手环10 Pro":{"orders":6,"revenue":2323.15,"avg_price":0}}},"17":{"orders":8,"revenue":3128.0,"products":{"小米手环10":{"orders":2,"revenue":758.0,"avg_price":0},"小米手环10 Pro":{"orders":6,"revenue":2370.0,"avg_price":0}}},"18":{"orders":10,"revenue":3828.3,"products":{"小米手环10":{"orders":2,"revenue":698.0,"avg_price":0},"小米手环10 Pro":{"orders":8,"revenue":3130.3,"avg_price":0}}},"19":{"orders":13,"revenue":4486.15,"products":{"小米手环10":{"orders":6,"revenue":1719.0,"avg_price":0},"小米手环10 Pro":{"orders":7,"revenue":2767.15,"avg_price":0}}},"20":{"orders":10,"revenue":3594.0,"products":{"小米手环10":{"orders":2,"revenue":492.0,"avg_price":0},"小米手环10 Pro":{"orders":8,"revenue":3102.0,"avg_price":0}}},"21":{"orders":14,"revenue":5017.0,"products":{"REDMI Watch 6":{"orders":1,"revenue":497.0,"avg_price":0},"小米手环10":{"orders":6,"revenue":1772.0,"avg_price":295.33},"小米手环10 Pro":{"orders":7,"revenue":2748.0,"avg_price":0}}},"22":{"orders":10,"revenue":3649.15,"products":{"小米手环10":{"orders":4,"revenue":1396.0,"avg_price":0},"小米手环10 Pro":{"orders":6,"revenue":2253.15,"avg_price":0}}},"23":{"orders":5,"revenue":1780.0,"products":{"小米手环10":{"orders":2,"revenue":588.0,"avg_price":0},"小米手环10 Pro":{"orders":3,"revenue":1192.0,"avg_price":0}}}}},"小米耳机官方直播间":{"_hourly_stats":{"0":{"orders":4,"revenue":1026.3,"products":{"REDMI Buds 8":{"orders":1,"revenue":229.0,"avg_price":0},"REDMI Buds 8 青春版":{"orders":2,"revenue":273.0,"avg_price":0},"Xiaomi 开放式耳机":{"orders":1,"revenue":524.3,"avg_price":0}}},"8":{"orders":6,"revenue":1629.0,"products":{"REDMI Buds 7S":{"orders":2,"revenue":358.0,"avg_price":0},"REDMI Buds 8":{"orders":1,"revenue":229.0,"avg_price":0},"REDMI Buds 8 Pro":{"orders":1,"revenue":374.0,"avg_price":0},"Xiaomi Buds 6":{"orders":1,"revenue":649.0,"avg_price":0},"充电配件":{"orders":1,"revenue":19.0,"avg_price":0}}},"9":{"orders":2,"revenue":238.0,"products":{"REDMI Buds 6 活力版":{"orders":1,"revenue":99.0,"avg_price":0},"REDMI Buds 8 青春版":{"orders":1,"revenue":139.0,"avg_price":0}}},"10":{"orders":4,"revenue":691.0,"products":{"REDMI Buds 8 Pro":{"orders":1,"revenue":374.0,"avg_price":0},"REDMI Buds 8 青春版":{"orders":3,"revenue":317.0,"avg_price":0}}},"11":{"orders":3,"revenue":317.0,"products":{"REDMI Buds 6 活力版":{"orders":1,"revenue":99.0,"avg_price":0},"REDMI Buds 8 活力版":{"orders":2,"revenue":218.0,"avg_price":0}}},"12":{"orders":6,"revenue":2359.0,"products":{"REDMI Buds 8 Pro":{"orders":1,"revenue":374.0,"avg_price":0},"REDMI Buds 8 活力版":{"orders":1,"revenue":109.0,"avg_price":0},"REDMI Buds 8 青春版":{"orders":2,"revenue":278.0,"avg_price":0},"Xiaomi 开放式耳机":{"orders":2,"revenue":1598.0,"avg_price":0}}},"13":{"orders":1,"revenue":138.6,"products":{"REDMI Buds 8 青春版":{"orders":1,"revenue":138.6,"avg_price":0}}},"14":{"orders":1,"revenue":798.6,"products":{"Xiaomi 开放式耳机":{"orders":1,"revenue":798.6,"avg_price":0}}},"18":{"orders":1,"revenue":374.0,"products":{"REDMI Buds 8 Pro":{"orders":1,"revenue":374.0,"avg_price":0}}},"19":{"orders":1,"revenue":139.0,"products":{"REDMI Buds 8 青春版":{"orders":1,"revenue":139.0,"avg_price":0}}},"20":{"orders":4,"revenue":2404.0,"products":{"Xiaomi 开放式耳机":{"orders":3,"revenue":2375.0,"avg_price":0},"充电配件":{"orders":1,"revenue":29.0,"avg_price":0}}},"21":{"orders":3,"revenue":967.0,"products":{"REDMI Buds 8 活力版":{"orders":2,"revenue":168.0,"avg_price":0},"Xiaomi 开放式耳机":{"orders":1,"revenue":799.0,"avg_price":0}}},"22":{"orders":1,"revenue":799.0,"products":{"Xiaomi 开放式耳机":{"orders":1,"revenue":799.0,"avg_price":0}}},"23":{"orders":7,"revenue":3048.0,"products":{"REDMI Buds 8":{"orders":1,"revenue":229.0,"avg_price":0},"REDMI Buds 8 Pro":{"orders":1,"revenue":374.0,"avg_price":0},"REDMI Buds 8 活力版":{"orders":1,"revenue":109.0,"avg_price":0},"REDMI Buds 8 青春版":{"orders":1,"revenue":139.0,"avg_price":0},"Xiaomi Buds 6":{"orders":1,"revenue":649.0,"avg_price":0},"Xiaomi 开放式耳机":{"orders":2,"revenue":1548.0,"avg_price":0}}}}}},"_hourly_stats":{"0":{"orders":164,"revenue":48890.95,"products":{"REDMI Buds 8":{"orders":1,"revenue":229.0,"avg_price":0},"REDMI Buds 8 青春版":{"orders":2,"revenue":273.0,"avg_price":0},"REDMI Watch 6":{"orders":17,"revenue":8856.4,"avg_price":0},"Xiaomi 开放式耳机":{"orders":1,"revenue":524.3,"avg_price":0},"【新品】Xiaomi Tag 智能定位 适配澎湃 ":{"orders":4,"revenue":137.78,"avg_price":0},"【新品】XiaomiTagBLE版本定位追踪器防丢":{"orders":1,"revenue":27.3,"avg_price":0},"【自营】Xiaomi Watch S5 时尚新品智":{"orders":2,"revenue":1922.15,"avg_price":0},"充电配件":{"orders":1,"revenue":19.9,"avg_price":0},"小米手环10":{"orders":114,"revenue":28989.32,"avg_price":254.29},"小米手环10 Pro":{"orders":21,"revenue":7911.8,"avg_price":0}}},"1":{"orders":95,"revenue":29252.28,"products":{"REDMI Buds 8 活力版":{"orders":3,"revenue":203.25,"avg_price":0},"REDMI Watch 6":{"orders":8,"revenue":4106.3,"avg_price":0},"REDMI 手环 3":{"orders":1,"revenue":137.0,"avg_price":0},"Xiaomi 开放式耳机":{"orders":1,"revenue":699.0,"avg_price":0},"【平台活动】小米手表 Xiaomi Watch S":{"orders":1,"revenue":1039.0,"avg_price":0},"【新品】XiaomiTagBLE版本定位追踪器防丢":{"orders":1,"revenue":35.0,"avg_price":0},"小米手环10":{"orders":59,"revenue":14878.18,"avg_price":0},"小米手环10 Pro":{"orders":21,"revenue":8154.55,"avg_price":0}}},"2":{"orders":47,"revenue":17097.7,"products":{"REDMI Buds 8 青春版":{"orders":1,"revenue":116.0,"avg_price":0},"REDMI Watch 6":{"orders":9,"revenue":4408.1,"avg_price":0},"【新品】XiaomiTagBLE版本定位追踪器防丢":{"orders":1,"revenue":35.6,"avg_price":0},"小米AI眼镜":{"orders":1,"revenue":1699.0,"avg_price":0},"小米手环10":{"orders":21,"revenue":5336.0,"avg_price":0},"小米手环10 Pro":{"orders":14,"revenue":5503.0,"avg_price":0}}},"3":{"orders":27,"revenue":10611.85,"products":{"REDMI Watch 6":{"orders":5,"revenue":2533.6,"avg_price":0},"【自营平台】XIaomI Watch S5 新品手":{"orders":1,"revenue":1169.1,"avg_price":0},"小米手环10":{"orders":10,"revenue":2588.0,"avg_price":0},"小米手环10 Pro":{"orders":10,"revenue":3992.15,"avg_price":0},"小米手环9 Pro":{"orders":1,"revenue":329.0,"avg_price":0}}},"4":{"orders":16,"revenue":6118.02,"products":{"REDMI Watch 6":{"orders":5,"revenue":2529.5,"avg_price":0},"小米手环10":{"orders":6,"revenue":1588.37,"avg_price":0},"小米手环10 Pro":{"orders":5,"revenue":2000.15,"avg_price":0}}},"5":{"orders":12,"revenue":4051.3,"products":{"REDMI Watch 6":{"orders":2,"revenue":1074.0,"avg_price":0},"小米手环10":{"orders":7,"revenue":1900.0,"avg_price":0},"小米手环10 Pro":{"orders":3,"revenue":1077.3,"avg_price":0}}},"6":{"orders":17,"revenue":6093.31,"products":{"REDMI Watch 6":{"orders":1,"revenue":529.0,"avg_price":0},"【平台活动】小米手表 Xiaomi Watch S":{"orders":1,"revenue":1239.0,"avg_price":0},"【新品】XiaomiTagBLE版本定位追踪器防丢":{"orders":2,"revenue":61.42,"avg_price":0},"小米手环10":{"orders":8,"revenue":2279.0,"avg_price":0},"小米手环10 Pro":{"orders":5,"revenue":1984.89,"avg_price":0}}},"7":{"orders":84,"revenue":24380.46,"products":{"REDMI Buds 8 活力版":{"orders":1,"revenue":73.88,"avg_price":0},"REDMI Watch 6":{"orders":11,"revenue":5465.25,"avg_price":0},"【新品】Xiaomi Tag 智能定位 适配澎湃 ":{"orders":1,"revenue":35.0,"avg_price":0},"【新品】XiaomiTagBLE版本定位追踪器防丢":{"orders":2,"revenue":56.0,"avg_price":0},"【新品上市】 Xiaomi Tag 适配澎湃 OS":{"orders":1,"revenue":22.4,"avg_price":0},"充电配件":{"orders":1,"revenue":15.9,"avg_price":0},"小米手环10":{"orders":48,"revenue":12341.52,"avg_price":0},"小米手环10 Pro":{"orders":16,"revenue":6297.78,"avg_price":0},"小米水浸卫士2   -默认-(69658)":{"orders":1,"revenue":42.0,"avg_price":0},"插线板/配件":{"orders":2,"revenue":30.73,"avg_price":0}}},"8":{"orders":80,"revenue":31055.97,"products":{"REDMI Buds 7S":{"orders":2,"revenue":358.0,"avg_price":0},"REDMI Buds 8":{"orders":1,"revenue":229.0,"avg_price":0},"REDMI Buds 8 Pro":{"orders":1,"revenue":374.0,"avg_price":0},"REDMI Watch 6":{"orders":24,"revenue":11963.1,"avg_price":0},"Xiaomi Buds 6":{"orders":1,"revenue":649.0,"avg_price":0},"【平台活动】小米手表 Xiaomi Watch S":{"orders":1,"revenue":1037.0,"avg_price":0},"【新品】XiaomiTagBLE版本定位追踪器防丢":{"orders":1,"revenue":27.0,"avg_price":0},"充电配件":{"orders":1,"revenue":19.0,"avg_price":0},"小米手环10":{"orders":14,"revenue":3791.48,"avg_price":0},"小米手环10 Pro":{"orders":33,"revenue":12571.39,"avg_price":0},"小米水浸卫士2   -默认-(69658)":{"orders":1,"revenue":37.0,"avg_price":0}}},"9":{"orders":165,"revenue":66753.91,"products":{"REDMI Buds 6 活力版":{"orders":1,"revenue":99.0,"avg_price":0},"REDMI Buds 8 活力版":{"orders":2,"revenue":154.0,"avg_price":0},"REDMI Buds 8 青春版":{"orders":1,"revenue":139.0,"avg_price":0},"REDMI Watch 6":{"orders":29,"revenue":14913.55,"avg_price":0},"Xiaomi 开放式耳机":{"orders":3,"revenue":2333.0,"avg_price":0},"【平台活动】小米手表 Xiaomi Watch S":{"orders":3,"revenue":3165.93,"avg_price":0},"【新品】XiaomiTagBLE版本定位追踪器防丢":{"orders":1,"revenue":32.0,"avg_price":0},"【自营】Xiaomi Watch S5 时尚新品智":{"orders":1,"revenue":880.6,"avg_price":0},"【补贴15%】XIaomI Watch S5 新品":{"orders":1,"revenue":1130.13,"avg_price":0},"充电配件":{"orders":1,"revenue":19.9,"avg_price":0},"小米手环10":{"orders":34,"revenue":9912.34,"avg_price":291.54},"小米手环10 Pro":{"orders":88,"revenue":33974.46,"avg_price":0}}},"10":{"orders":126,"revenue":51696.72,"products":{"REDMI Buds 8 Pro":{"orders":1,"revenue":374.0,"avg_price":0},"REDMI Buds 8 活力版":{"orders":2,"revenue":144.37,"avg_price":0},"REDMI Buds 8 青春版":{"orders":4,"revenue":446.0,"avg_price":0},"REDMI Watch 6":{"orders":27,"revenue":13816.6,"avg_price":0},"Xiaomi 开放式耳机":{"orders":5,"revenue":3800.99,"avg_price":0},"【平台活动】小米手表 Xiaomi Watch S":{"orders":1,"revenue":903.93,"avg_price":0},"【自营】Xiaomi Watch S5 时尚新品智":{"orders":1,"revenue":1002.0,"avg_price":0},"充电配件":{"orders":1,"revenue":29.9,"avg_price":0},"小米手环10":{"orders":14,"revenue":4296.1,"avg_price":0},"小米手环10 Pro":{"orders":70,"revenue":26882.83,"avg_price":0}}},"11":{"orders":128,"revenue":55824.08,"products":{"REDMI Buds 6 活力版":{"orders":1,"revenue":99.0,"avg_price":0},"REDMI Buds 8 活力版":{"orders":3,"revenue":292.0,"avg_price":0},"REDMI Watch 6":{"orders":23,"revenue":11970.5,"avg_price":0},"Xiaomi 开放式耳机":{"orders":2,"revenue":1567.0,"avg_price":0},"【平台活动】小米手表 Xiaomi Watch S":{"orders":8,"revenue":8574.93,"avg_price":0},"【平台自营】小米手表 Xiaomi Watch S":{"orders":1,"revenue":1077.93,"avg_price":0},"小米手环10":{"orders":25,"revenue":7110.11,"avg_price":284.4},"小米手环10 Pro":{"orders":64,"revenue":24803.61,"avg_price":0},"小米手环9 Pro":{"orders":1,"revenue":329.0,"avg_price":0}}},"12":{"orders":115,"revenue":46662.11,"products":{"REDMI Buds 6 活力版":{"orders":1,"revenue":64.0,"avg_price":0},"REDMI Buds 8 Pro":{"orders":2,"revenue":748.0,"avg_price":0},"REDMI Buds 8 活力版":{"orders":4,"revenue":327.83,"avg_price":0},"REDMI Buds 8 青春版":{"orders":2,"revenue":278.0,"avg_price":0},"REDMI Watch 6":{"orders":20,"revenue":10615.1,"avg_price":0},"Xiaomi 开放式耳机":{"orders":5,"revenue":3906.0,"avg_price":0},"【平台活动】小米手表 Xiaomi Watch S":{"orders":2,"revenue":2140.93,"avg_price":0},"【活动】小米智能摄像机 4C 高清超清3.5K画质":{"orders":1,"revenue":193.0,"avg_price":0},"小米手环10":{"orders":25,"revenue":7184.0,"avg_price":0},"小米手环10 Pro":{"orders":52,"revenue":20881.25,"avg_price":0},"小米手环9 Pro":{"orders":1,"revenue":324.0,"avg_price":0}}},"13":{"orders":96,"revenue":37313.37,"products":{"REDMI Buds 8 活力版":{"orders":1,"revenue":71.0,"avg_price":0},"REDMI Buds 8 青春版":{"orders":2,"revenue":230.6,"avg_price":0},"REDMI Watch 6":{"orders":11,"revenue":5735.3,"avg_price":0},"Xiaomi Buds 6":{"orders":1,"revenue":635.0,"avg_price":0},"Xiaomi 开放式耳机":{"orders":2,"revenue":1598.0,"avg_price":0},"【平台活动】小米手表 Xiaomi Watch S":{"orders":1,"revenue":903.93,"avg_price":0},"小米手环10":{"orders":20,"revenue":5539.04,"avg_price":0},"小米手环10 Pro":{"orders":58,"revenue":22600.5,"avg_price":0}}},"14":{"orders":109,"revenue":44870.26,"products":{"REDMI Buds 6 活力版":{"orders":1,"revenue":44.8,"avg_price":0},"REDMI Watch 6":{"orders":22,"revenue":11627.6,"avg_price":0},"Xiaomi 开放式耳机":{"orders":4,"revenue":3185.31,"avg_price":0},"【新品上市】 Xiaomi Tag 适配澎湃 OS":{"orders":1,"revenue":32.0,"avg_price":0},"小米手环10":{"orders":21,"revenue":6283.97,"avg_price":0},"小米手环10 Pro":{"orders":60,"revenue":23696.58,"avg_price":0}}},"15":{"orders":104,"revenue":42379.24,"products":{"REDMI Buds 8 Pro":{"orders":1,"revenue":374.0,"avg_price":0},"REDMI Buds 8 青春版":{"orders":2,"revenue":278.0,"avg_price":0},"REDMI Watch 6":{"orders":29,"revenue":15040.08,"avg_price":0},"Xiaomi 开放式耳机":{"orders":2,"revenue":1553.0,"avg_price":0},"【加黑链接】小米手表 Xiaomi Watch S":{"orders":1,"revenue":1039.0,"avg_price":0},"【平台自营】小米手表 Xiaomi Watch S":{"orders":1,"revenue":1077.93,"avg_price":0},"充电配件":{"orders":1,"revenue":19.9,"avg_price":0},"小米手环10":{"orders":31,"revenue":8946.29,"avg_price":0},"小米手环10 Pro":{"orders":36,"revenue":14051.04,"avg_price":0}}},"16":{"orders":97,"revenue":39117.29,"products":{"REDMI Watch 6":{"orders":32,"revenue":16264.8,"avg_price":0},"Xiaomi 开放式耳机":{"orders":1,"revenue":797.0,"avg_price":0},"充电配件":{"orders":2,"revenue":39.8,"avg_price":0},"小米手环10":{"orders":23,"revenue":7296.38,"avg_price":317.23},"小米手环10 Pro":{"orders":38,"revenue":14694.41,"avg_price":0},"插线板/配件":{"orders":1,"revenue":24.9,"avg_price":0}}},"17":{"orders":86,"revenue":35198.67,"products":{"REDMI Buds 8 活力版":{"orders":1,"revenue":81.06,"avg_price":0},"REDMI Watch 6":{"orders":17,"revenue":8637.09,"avg_price":0},"Xiaomi 开放式耳机":{"orders":4,"revenue":3115.0,"avg_price":0},"小米手环10":{"orders":20,"revenue":6232.47,"avg_price":0},"小米手环10 Pro":{"orders":44,"revenue":17133.05,"avg_price":0}}},"18":{"orders":78,"revenue":33422.39,"products":{"REDMI Buds 8 Pro":{"orders":1,"revenue":374.0,"avg_price":0},"REDMI Watch 6":{"orders":19,"revenue":9501.6,"avg_price":0},"Xiaomi 开放式耳机":{"orders":2,"revenue":1530.0,"avg_price":0},"小米AI眼镜":{"orders":1,"revenue":1697.0,"avg_price":0},"小米手环10":{"orders":14,"revenue":4552.05,"avg_price":0},"小米手环10 Pro":{"orders":40,"revenue":15445.74,"avg_price":0},"小米手环9 Pro":{"orders":1,"revenue":322.0,"avg_price":0}}},"19":{"orders":107,"revenue":45898.76,"products":{"REDMI Buds 8 活力版":{"orders":1,"revenue":79.0,"avg_price":0},"REDMI Buds 8 青春版":{"orders":2,"revenue":247.0,"avg_price":0},"REDMI Watch 6":{"orders":20,"revenue":10476.7,"avg_price":0},"Xiaomi 开放式耳机":{"orders":6,"revenue":4682.0,"avg_price":0},"【加黑链接】小米手表 Xiaomi Watch S":{"orders":4,"revenue":4156.0,"avg_price":0},"小米手环10":{"orders":25,"revenue":7462.6,"avg_price":298.5},"小米手环10 Pro":{"orders":47,"revenue":18332.46,"avg_price":0},"小米手环9 Pro":{"orders":1,"revenue":324.0,"avg_price":0},"耳机配件":{"orders":1,"revenue":139.0,"avg_price":0}}},"20":{"orders":117,"revenue":49558.65,"products":{"REDMI Buds 8 青春版":{"orders":1,"revenue":139.0,"avg_price":0},"REDMI Watch 6":{"orders":27,"revenue":14143.5,"avg_price":0},"Xiaomi 开放式耳机":{"orders":8,"revenue":6282.0,"avg_price":0},"充电配件":{"orders":1,"revenue":29.0,"avg_price":0},"小米手环10":{"orders":25,"revenue":7778.65,"avg_price":311.15},"小米手环10 Pro":{"orders":55,"revenue":21186.5,"avg_price":0}}},"21":{"orders":124,"revenue":49789.94,"products":{"REDMI Buds 8 活力版":{"orders":3,"revenue":250.93,"avg_price":0},"REDMI Watch 6":{"orders":18,"revenue":9333.7,"avg_price":0},"REDMI 手环 3":{"orders":1,"revenue":139.0,"avg_price":0},"Xiaomi 开放式耳机":{"orders":4,"revenue":3196.0,"avg_price":0},"【加黑链接】小米手表 Xiaomi Watch S":{"orders":4,"revenue":4356.0,"avg_price":0},"【新品】XiaomiTagBLE版本定位追踪器防丢":{"orders":1,"revenue":37.0,"avg_price":0},"小米小背包 10L -亮蓝色-(19508)":{"orders":1,"revenue":21.0,"avg_price":0},"小米小背包 10L -黄色-(19512)":{"orders":1,"revenue":21.0,"avg_price":0},"小米手环10":{"orders":29,"revenue":8867.0,"avg_price":305.76},"小米手环10 Pro":{"orders":60,"revenue":23404.41,"avg_price":0},"插线板/配件":{"orders":1,"revenue":24.9,"avg_price":0},"耳机配件":{"orders":1,"revenue":139.0,"avg_price":0}}},"22":{"orders":82,"revenue":33885.4,"products":{"REDMI Buds 8 活力版":{"orders":1,"revenue":76.0,"avg_price":0},"REDMI Watch 6":{"orders":17,"revenue":8963.3,"avg_price":0},"Xiaomi 开放式耳机":{"orders":4,"revenue":3124.0,"avg_price":0},"【平台自营】小米手表 Xiaomi Watch S":{"orders":1,"revenue":935.1,"avg_price":0},"小米手环10":{"orders":19,"revenue":5718.74,"avg_price":0},"小米手环10 Pro":{"orders":39,"revenue":14739.26,"avg_price":0},"小米手环9 Pro":{"orders":1,"revenue":329.0,"avg_price":0}}},"23":{"orders":80,"revenue":33007.21,"products":{"REDMI Buds 8":{"orders":1,"revenue":229.0,"avg_price":0},"REDMI Buds 8 Pro":{"orders":1,"revenue":374.0,"avg_price":0},"REDMI Buds 8 活力版":{"orders":2,"revenue":187.0,"avg_price":0},"REDMI Buds 8 青春版":{"orders":1,"revenue":139.0,"avg_price":0},"REDMI Watch 6":{"orders":18,"revenue":9168.3,"avg_price":0},"Xiaomi Buds 6":{"orders":1,"revenue":649.0,"avg_price":0},"Xiaomi 开放式耳机":{"orders":4,"revenue":3127.0,"avg_price":0},"【加黑链接】小米手表 Xiaomi Watch S":{"orders":1,"revenue":1039.0,"avg_price":0},"小米手环10":{"orders":16,"revenue":4913.97,"avg_price":307.12},"小米手环10 Pro":{"orders":34,"revenue":12896.94,"avg_price":0},"小米手环9 Pro":{"orders":1,"revenue":284.0,"avg_price":0}}}}}